fastshelf/PlyvelDB.py
fastshelf/RocksDB.py
fastshelf/__init__.py
fastshelf/fastshelf.py
fastshelf-0.1.4.dist-info/LICENSE
fastshelf-0.1.4.dist-info/METADATA
fastshelf-0.1.4.dist-info/WHEEL
fastshelf-0.1.4.dist-info/top_level.txt
fastshelf-0.1.4.dist-info/RECORD
