Metadata-Version: 2.1
Name: fastshelf
Version: 0.1.4
Summary: high performance persistent python dict with choices of backend
Home-page: https://github.com/ligonliu/fastshelf
Author: Ligon Liu
Author-email: ligonliu1@gmail.com
License: UNKNOWN
Project-URL: Bug Tracker, https://github.com/ligonliu/fastshelf/issues
Platform: UNKNOWN
Classifier: Programming Language :: Python :: 3
Classifier: License :: OSI Approved :: MIT License
Classifier: Operating System :: OS Independent
Requires-Python: >=3.4
License-File: LICENSE
Requires-Dist: bidict
